builton_sdk/__init__.py
builton_sdk/main.py
builton_sdk/api_models/__init__.py
builton_sdk/api_models/_component.py
builton_sdk/api_models/ai_model.py
builton_sdk/api_models/company.py
builton_sdk/api_models/component.py
builton_sdk/api_models/event.py
builton_sdk/api_models/order.py
builton_sdk/api_models/payment.py
builton_sdk/api_models/payment_method.py
builton_sdk/api_models/plan.py
builton_sdk/api_models/product.py
builton_sdk/api_models/provider.py
builton_sdk/api_models/resource.py
builton_sdk/api_models/subscription.py
builton_sdk/api_models/tag.py
builton_sdk/api_models/user.py
builton_sdk/api_models/webhook.py
builton_sdk/utils/__init__.py
builton_sdk/utils/request.py
builton_sdk/utils/rest_functions.py
examples/__init__.py
examples/example.py
examples/logging_example.py
examples/test_logging.py
tests/__init__.py
tests/conftest.py
tests/integration/__init__.py
tests/integration/config.py
tests/integration/test_order.py
tests/integration/test_payment.py
tests/integration/test_payment_method.py
tests/integration/test_product.py
tests/integration/test_subscription.py
tests/integration/test_user.py
tests/unit/__init__.py
tests/unit/test_ai_model.py
tests/unit/test_company.py
tests/unit/test_components.py
tests/unit/test_event.py
tests/unit/test_main.py
tests/unit/test_order.py
tests/unit/test_order_model.py
tests/unit/test_payment.py
tests/unit/test_payment_method.py
tests/unit/test_plan.py
tests/unit/test_product.py
tests/unit/test_provider.py
tests/unit/test_request.py
tests/unit/test_resource.py
tests/unit/test_subscription.py
tests/unit/test_tag.py
tests/unit/test_user_model.py
tests/unit/test_webhook.py
builton_sdk-0.3.1.dist-info/LICENSE.md
builton_sdk-0.3.1.dist-info/METADATA
builton_sdk-0.3.1.dist-info/WHEEL
builton_sdk-0.3.1.dist-info/top_level.txt
builton_sdk-0.3.1.dist-info/RECORD
