Metadata-Version: 2.1
Name: builton-sdk
Version: 0.3.1
Summary: BuiltOn Python SDK
Home-page: https://github.com/BuiltonDev/python-sdk
Author: BuiltOn
Author-email: hello@builton.dev
License: MIT
Project-URL: Bug Tracker, https://github.com/BuiltonDev/python-sdk/issues
Project-URL: Documentation, https://docs.builton.dev
Keywords: builton api sdk ai
Platform: UNKNOWN
Classifier: Development Status :: 4 - Beta
Classifier: Intended Audience :: Developers
Classifier: License :: OSI Approved :: MIT License
Classifier: Operating System :: OS Independent
Classifier: Programming Language :: Python
Classifier: Programming Language :: Python :: 2
Classifier: Programming Language :: Python :: 2.7
Classifier: Programming Language :: Python :: 3
Classifier: Programming Language :: Python :: 3.0
Classifier: Programming Language :: Python :: 3.1
Classifier: Programming Language :: Python :: 3.2
Classifier: Programming Language :: Python :: 3.3
Classifier: Programming Language :: Python :: 3.4
Classifier: Programming Language :: Python :: 3.5
Classifier: Programming Language :: Python :: 3.6
Classifier: Programming Language :: Python :: 3.7
Classifier: Programming Language :: Python :: Implementation :: PyPy
Classifier: Topic :: Software Development :: Libraries :: Python Modules
Requires-Python: >=2.7
Requires-Dist: requests
